Workbook

Sheet Financials
C2: F2022A | D2: F2023A | E2: F2024A | F2: F2025E | G2: F2026E | H2: F2027E | I2: F2028E | J2: F2029E
B3: Henderson Manufacturing
B4: Income Statement
B6: ($ Millions)
B8: Gross Revenue | C8: 244.8 | D8: 269.3 | E8: 239.2 | F8: =E8*(1+Assumptions!H8) -> 246.376 | G8: =F8*(1+Assumptions!I8) -> 254.99916 | H8: =G8*(1+Assumptions!J8) -> 265.19913 | I8: =H8*(1+Assumptions!K8) -> 277.13309 | J8: =I8*(1+Assumptions!L8) -> 290.98974
B9: Freight & Warehousing | C9: 31.3 | D9: 32.7 | E9: 34.4 | F9: =F8*Assumptions!H9 -> 33.26076 | G9: =G8*Assumptions!I9 -> 33.914888 | H9: =H8*Assumptions!J9 -> 34.475886 | I9: =I8*Assumptions!K9 -> 36.027301 | J9: =J8*Assumptions!L9 -> 37.828666
B10: Net Revenue | C10: =C8-C9 -> 213.5 | D10: =D8-D9 -> 236.6 | E10: =E8-E9 -> 204.8 | F10: =F8-F9 -> 213.11524 | G10: =G8-G9 -> 221.08427 | H10: =H8-H9 -> 230.72324 | I10: =I8-I9 -> 241.10579 | J10: =J8-J9 -> 253.16108
B12: Cost of Sales | C12: 159.9 | D12: 164.6 | E12: 167.9 | F12: =F10*Assumptions!H10 -> 166.22989 | G12: =G10*Assumptions!I10 -> 168.02405 | H12: =H10*Assumptions!J10 -> 170.7352 | I12: =I10*Assumptions!K10 -> 176.00722 | J12: =J10*Assumptions!L10 -> 182.27597
B13: SG&A | C13: 3.4 | D13: 3.6 | E13: 3.8 | F13: =F10*Assumptions!H11 -> 3.6229591 | G13: =G10*Assumptions!I11 -> 3.7584326 | H13: =H10*Assumptions!J11 -> 3.9222951 | I13: =I10*Assumptions!K11 -> 4.0987984 | J13: =J10*Assumptions!L11 -> 4.3037383
B14: Total Costs | C14: =C12+C13 -> 163.3 | D14: =D12+D13 -> 168.2 | E14: =E12+E13 -> 171.7 | F14: =F12+F13 -> 169.85285 | G14: =G12+G13 -> 171.78248 | H14: =H12+H13 -> 174.65749 | I14: =I12+I13 -> 180.10602 | J14: =J12+J13 -> 186.57971
B16: Cost Adjustments - Gain/(Loss) | C16: 0 | D16: 0 | E16: 0 | F16: =Assumptions!H12 -> 0 | G16: =Assumptions!I12 -> 0 | H16: =Assumptions!J12 -> 0 | I16: =Assumptions!K12 -> 0 | J16: =Assumptions!L12 -> 0
B17: EBITDA | C17: =C10-C14+C16 -> 50.2 | D17: =D10-D14+D16 -> 68.4 | E17: =E10-E14+E16 -> 33.1 | F17: =F10-F14+F16 -> 43.262394 | G17: =G10-G14+G16 -> 49.301793 | H17: =H10-H14+H16 -> 56.065747 | I17: =I10-I14+I16 -> 60.999764 | J17: =J10-J14+J16 -> 66.581363
B19: Depreciation | C19: 15.4 | D19: 15.5 | E19: 15.8 | F19: =Assumptions!H15 -> 16 | G19: =Assumptions!I15 -> 16.2 | H19: =Assumptions!J15 -> 16.4 | I19: =Assumptions!K15 -> 16.5 | J19: =Assumptions!L15 -> 16.7
B20: EBIT | C20: =C17-C19 -> 34.8 | D20: =D17-D19 -> 52.9 | E20: =E17-E19 -> 17.3 | F20: =F17-F19 -> 27.262394 | G20: =G17-G19 -> 33.101793 | H20: =H17-H19 -> 39.665747 | I20: =I17-I19 -> 44.499764 | J20: =J17-J19 -> 49.881363
B22: Interest Expense | C22: 15 | D22: 15 | E22: 14 | F22: =Assumptions!H30*(E83+F83)/2 -> 12.1875 | G22: =Assumptions!I30*(F83+G83)/2 -> 10.5625 | H22: =Assumptions!J30*(G83+H83)/2 -> 8.9375 | I22: =Assumptions!K30*(H83+I83)/2 -> 7.3125 | J22: =Assumptions!L30*(I83+J83)/2 -> 5.6875
B23: EBT | C23: =C20-C22 -> 19.8 | D23: =D20-D22 -> 37.9 | E23: =E20-E22 -> 3.3 | F23: =F20-F22 -> 15.074894 | G23: =G20-G22 -> 22.539293 | H23: =H20-H22 -> 30.728247 | I23: =I20-I22 -> 37.187264 | J23: =J20-J22 -> 44.193863
B25: Current Taxes | C25: 3 | D25: 8 | E25: 0 | F25: =IF(F23>0,F23*Assumptions!H16*Assumptions!H17,0) -> 2.5325821 | G25: =IF(G23>0,G23*Assumptions!I16*Assumptions!I17,0) -> 3.7866012 | H25: =IF(H23>0,H23*Assumptions!J16*Assumptions!J17,0) -> 5.1623455 | I25: =IF(I23>0,I23*Assumptions!K16*Assumptions!K17,0) -> 6.2474603 | J25: =IF(J23>0,J23*Assumptions!L16*Assumptions!L17,0) -> 7.4245689
B26: Deferred Income Taxes | C26: 2.7 | D26: 6.2 | E26: 1.1 | F26: =IF(F23>0,F23*Assumptions!H16*(1-Assumptions!H17),0) -> 1.6883881 | G26: =IF(G23>0,G23*Assumptions!I16*(1-Assumptions!I17),0) -> 2.5244008 | H26: =IF(H23>0,H23*Assumptions!J16*(1-Assumptions!J17),0) -> 3.4415637 | I26: =IF(I23>0,I23*Assumptions!K16*(1-Assumptions!K17),0) -> 4.1649735 | J26: =IF(J23>0,J23*Assumptions!L16*(1-Assumptions!L17),0) -> 4.9497126
B27: Total Income Taxes | C27: =C25+C26 -> 5.7 | D27: =D25+D26 -> 14.2 | E27: =E25+E26 -> 1.1 | F27: =F25+F26 -> 4.2209702 | G27: =G25+G26 -> 6.3110019 | H27: =H25+H26 -> 8.6039092 | I27: =I25+I26 -> 10.412434 | J27: =J25+J26 -> 12.374282
B29: Net Income to Common | C29: =C23-C27 -> 14.1 | D29: =D23-D27 -> 23.7 | E29: =E23-E27 -> 2.2 | F29: =F23-F27 -> 10.853923 | G29: =G23-G27 -> 16.228291 | H29: =H23-H27 -> 22.124338 | I29: =I23-I27 -> 26.77483 | J29: =J23-J27 -> 31.819581
C32: F2022A | D32: F2023A | E32: F2024A | F32: F2025E | G32: F2026E | H32: F2027E | I32: F2028E | J32: F2029E
B33: Cash Flow Statement
B35: Operating Activities
B36: Net Income | C36: 14.1 | D36: 23.7 | E36: 2.2 | F36: =F29 -> 10.853923 | G36: =G29 -> 16.228291 | H36: =H29 -> 22.124338 | I36: =I29 -> 26.77483 | J36: =J29 -> 31.819581
B37: Depreciation | C37: 15.4 | D37: 15.5 | E37: 15.8 | F37: =F19 -> 16 | G37: =G19 -> 16.2 | H37: =H19 -> 16.4 | I37: =I19 -> 16.5 | J37: =J19 -> 16.7
B38: Deferred Income Taxes | C38: 2.7 | D38: 6.2 | E38: 1.1 | F38: =F26 -> 1.6883881 | G38: =G26 -> 2.5244008 | H38: =H26 -> 3.4415637 | I38: =I26 -> 4.1649735 | J38: =J26 -> 4.9497126
B39: Changes in Working Capital | C39: 0 | D39: 0 | E39: 0 | F39: =-((F64-E64)+(F65-E65)+(F66-E66)+(F67-E67)-(F78-E78)-(F79-E79)) -> 1.2827171 | G39: =-((G64-F64)+(G65-F65)+(G66-F66)+(G67-F67)-(G78-F78)-(G79-F79)) -> -1.6165177 | H39: =-((H64-G64)+(H65-G65)+(H66-G66)+(H67-G67)-(H78-G78)-(H79-G79)) -> -0.44245358 | I39: =-((I64-H64)+(I65-H65)+(I66-H66)+(I67-H67)-(I78-H78)-(I79-H79)) -> -2.3462341 | J39: =-((J64-I64)+(J65-I65)+(J66-I66)+(J67-I67)-(J78-I78)-(J79-I79)) -> -2.7383672
B40: Operating Cash Flow | C40: =C36+C37+C38+C39 -> 32.2 | D40: =D36+D37+D38+D39 -> 45.4 | E40: =E36+E37+E38+E39 -> 19.1 | F40: =F36+F37+F38+F39 -> 29.825029 | G40: =G36+G37+G38+G39 -> 33.336174 | H40: =H36+H37+H38+H39 -> 41.523448 | I40: =I36+I37+I38+I39 -> 45.093569 | J40: =J36+J37+J38+J39 -> 50.730927
B42: Investing Activities
B43: CAPEX | C43: -14.1 | D43: -15 | E43: -15.5 | F43: =-Assumptions!H28 -> -16 | G43: =-Assumptions!I28 -> -16.2 | H43: =-Assumptions!J28 -> -16.5 | I43: =-Assumptions!K28 -> -16.5 | J43: =-Assumptions!L28 -> -17
B44: Other | C44: -5 | D44: 4 | E44: 3 | F44: =Assumptions!H29 -> 3 | G44: =Assumptions!I29 -> 3 | H44: =Assumptions!J29 -> 0 | I44: =Assumptions!K29 -> 0 | J44: =Assumptions!L29 -> 0
B45: Investing Cash Flow | C45: =C43+C44 -> -19.1 | D45: =D43+D44 -> -11 | E45: =E43+E44 -> -12.5 | F45: =F43+F44 -> -13 | G45: =G43+G44 -> -13.2 | H45: =H43+H44 -> -16.5 | I45: =I43+I44 -> -16.5 | J45: =J43+J44 -> -17
B47: Financing Activities
B48: Revolver Issuance / (Repayment) | C48: 0 | D48: 0 | E48: 0 | F48: =Assumptions!H32 -> 0 | G48: =Assumptions!I32 -> 0 | H48: =Assumptions!J32 -> 0 | I48: =Assumptions!K32 -> 0 | J48: =Assumptions!L32 -> 0
B49: Total Term Debt Issuance / (Repayment) | C49: -25 | D49: -25 | E49: -25 | F49: =-Assumptions!H31 -> -25 | G49: =-Assumptions!I31 -> -25 | H49: =-Assumptions!J31 -> -25 | I49: =-Assumptions!K31 -> -25 | J49: =-Assumptions!L31 -> -25
B50: Common Shares Issuance/ (Buy-Back) | C50: 0 | D50: 0 | E50: 0 | F50: =Assumptions!H33 -> 0 | G50: =Assumptions!I33 -> 0 | H50: =Assumptions!J33 -> 0 | I50: =Assumptions!K33 -> 0 | J50: =Assumptions!L33 -> 0
B51: Common Dividends | C51: -2.8 | D51: -4.7 | E51: -2.4 | F51: =-Assumptions!H34 -> -3 | G51: =-Assumptions!I34 -> -3 | H51: =-Assumptions!J34 -> -3.5 | I51: =-Assumptions!K34 -> -3.5 | J51: =-Assumptions!L34 -> -4
B52: Financing Cash Flow | C52: =C48+C49+C50+C51 -> -27.8 | D52: =D48+D49+D50+D51 -> -29.7 | E52: =E48+E49+E50+E51 -> -27.4 | F52: =F48+F49+F50+F51 -> -28 | G52: =G48+G49+G50+G51 -> -28 | H52: =H48+H49+H50+H51 -> -28.5 | I52: =I48+I49+I50+I51 -> -28.5 | J52: =J48+J49+J50+J51 -> -29
B54: Change in Cash Position | C54: =C40+C45+C52 -> -14.7 | D54: =D40+D45+D52 -> 4.7 | E54: =E40+E45+E52 -> -20.8 | F54: =F40+F45+F52 -> -11.174971 | G54: =G40+G45+G52 -> -7.8638263 | H54: =H40+H45+H52 -> -3.4765518 | I54: =I40+I45+I52 -> 0.093569372 | J54: =J40+J45+J52 -> 4.7309266
B55: Beginning Cash | C55: 31.1 | D55: 16.4 | E55: 21.1 | F55: =E56 -> 0.3 | G55: =F56 -> -10.874971 | H55: =G56 -> -18.738798 | I55: =H56 -> -22.215349 | J55: =I56 -> -22.12178
B56: Ending Cash | C56: =C55+C54 -> 16.4 | D56: =D55+D54 -> 21.1 | E56: =E55+E54 -> 0.3 | F56: =F55+F54 -> -10.874971 | G56: =G55+G54 -> -18.738798 | H56: =H55+H54 -> -22.215349 | I56: =I55+I54 -> -22.12178 | J56: =J55+J54 -> -17.390853
C59: F2022A | D59: F2023A | E59: F2024A | F59: F2025E | G59: F2026E | H59: F2027E | I59: F2028E | J59: F2029E
B60: Balance Sheet
B62: ASSETS
B63: Cash and Equivalents | C63: 16.4 | D63: 21.1 | E63: 0.3 | F63: =F56 -> -10.874971 | G63: =G56 -> -18.738798 | H63: =H56 -> -22.215349 | I63: =I56 -> -22.12178 | J63: =J56 -> -17.390853
B64: Accounts Receivable | C64: 27 | D64: 27.8 | E64: 28.3 | F64: =F10*Assumptions!H20/365 -> 26.858359 | G64: =G10*Assumptions!I20/365 -> 27.862675 | H64: =H10*Assumptions!J20/365 -> 28.445331 | I64: =I10*Assumptions!K20/365 -> 29.725371 | J64: =J10*Assumptions!L20/365 -> 31.211639
B65: Inventory | C65: 36.5 | D65: 36.1 | E65: 35.1 | F65: =F12*Assumptions!H21/365 -> 35.523099 | G65: =G12*Assumptions!I21/365 -> 35.906509 | H65: =H12*Assumptions!J21/365 -> 35.550343 | I65: =I12*Assumptions!K21/365 -> 36.648079 | J65: =J12*Assumptions!L21/365 -> 37.953353
B66: Prepaid Expenses | C66: 14.6 | D66: 14.4 | E66: 14.9 | F66: =F10*Assumptions!H22 -> 14.918067 | G66: =G10*Assumptions!I22 -> 15.475899 | H66: =H10*Assumptions!J22 -> 16.150627 | I66: =I10*Assumptions!K22 -> 16.877405 | J66: =J10*Assumptions!L22 -> 17.721275
B67: Other | C67: 1.4 | D67: 1.8 | E67: 1.2 | F67: =F10*Assumptions!H23 -> 1.4918067 | G67: =G10*Assumptions!I23 -> 1.5475899 | H67: =H10*Assumptions!J23 -> 1.6150627 | I67: =I10*Assumptions!K23 -> 1.6877405 | J67: =J10*Assumptions!L23 -> 1.7721275
B68: Total Current Assets | C68: =C63+C64+C65+C66+C67 -> 95.9 | D68: =D63+D64+D65+D66+D67 -> 101.2 | E68: =E63+E64+E65+E66+E67 -> 79.8 | F68: =F63+F64+F65+F66+F67 -> 67.91636 | G68: =G63+G64+G65+G66+G67 -> 62.053875 | H68: =H63+H64+H65+H66+H67 -> 59.546014 | I68: =I63+I64+I65+I66+I67 -> 62.816816 | J68: =J63+J64+J65+J66+J67 -> 71.267542
B70: Net PP&E | C70: 398.5 | D70: 398 | E70: 397.7 | F70: =E70-F43-F19 -> 397.7 | G70: =F70-G43-G19 -> 397.7 | H70: =G70-H43-H19 -> 397.8 | I70: =H70-I43-I19 -> 397.8 | J70: =I70-J43-J19 -> 398.1
B71: Other | C71: 19 | D71: 15 | E71: 12 | F71: =Assumptions!H35 -> 9 | G71: =Assumptions!I35 -> 6 | H71: =Assumptions!J35 -> 6 | I71: =Assumptions!K35 -> 6 | J71: =Assumptions!L35 -> 6
B72: Total Long Term Assets | C72: =C70+C71 -> 417.5 | D72: =D70+D71 -> 413 | E72: =E70+E71 -> 409.7 | F72: =F70+F71 -> 406.7 | G72: =G70+G71 -> 403.7 | H72: =H70+H71 -> 403.8 | I72: =I70+I71 -> 403.8 | J72: =J70+J71 -> 404.1
B74: Total Assets | C74: =C68+C72 -> 513.4 | D74: =D68+D72 -> 514.2 | E74: =E68+E72 -> 489.5 | F74: =F68+F72 -> 474.61636 | G74: =G68+G72 -> 465.75388 | H74: =H68+H72 -> 463.34601 | I74: =I68+I72 -> 466.61682 | J74: =J68+J72 -> 475.36754
B76: LIABILITIES AND EQUITY
B77: Bank Debt - Revolver | C77: 0 | D77: 0 | E77: 0 | F77: =E77+F48 -> 0 | G77: =F77+G48 -> 0 | H77: =G77+H48 -> 0 | I77: =H77+I48 -> 0 | J77: =I77+J48 -> 0
B78: Accounts Payable | C78: 18.3 | D78: 18.7 | E78: 18.2 | F78: =F12*Assumptions!H24/365 -> 18.672398 | G78: =G12*Assumptions!I24/365 -> 18.873934 | H78: =H12*Assumptions!J24/365 -> 19.178474 | I78: =I12*Assumptions!K24/365 -> 19.770674 | J78: =J12*Assumptions!L24/365 -> 20.474835
B79: Other | C79: 4.7 | D79: 4.9 | E79: 4.8 | F79: =F10*Assumptions!H25 -> 4.9016505 | G79: =G10*Assumptions!I25 -> 5.0849382 | H79: =H10*Assumptions!J25 -> 5.3066345 | I79: =I10*Assumptions!K25 -> 5.5454331 | J79: =J10*Assumptions!L25 -> 5.8227047
B80: Total Current Liabilities | C80: =C77+C78+C79 -> 23 | D80: =D77+D78+D79 -> 23.6 | E80: =E77+E78+E79 -> 23 | F80: =F77+F78+F79 -> 23.574049 | G80: =G77+G78+G79 -> 23.958872 | H80: =H77+H78+H79 -> 24.485109 | I80: =I77+I78+I79 -> 25.316108 | J80: =J77+J78+J79 -> 26.29754
B82: Deferred Income Taxes | C82: 0.7 | D82: 6.9 | E82: 8 | F82: =E82+F38 -> 9.6883881 | G82: =F82+G38 -> 12.212789 | H82: =G82+H38 -> 15.654353 | I82: =H82+I38 -> 19.819326 | J82: =I82+J38 -> 24.769039
B83: Senior Secured Term Debt | C83: 250 | D83: 225 | E83: 200 | F83: =E83+F49 -> 175 | G83: =F83+G49 -> 150 | H83: =G83+H49 -> 125 | I83: =H83+I49 -> 100 | J83: =I83+J49 -> 75
B84: Total Long Term Liabilities | C84: =C82+C83 -> 250.7 | D84: =D82+D83 -> 231.9 | E84: =E82+E83 -> 208 | F84: =F82+F83 -> 184.68839 | G84: =G82+G83 -> 162.21279 | H84: =H82+H83 -> 140.65435 | I84: =I82+I83 -> 119.81933 | J84: =J82+J83 -> 99.769039
B86: Total Liabilities | C86: =C80+C84 -> 273.7 | D86: =D80+D84 -> 255.5 | E86: =E80+E84 -> 231 | F86: =F80+F84 -> 208.26244 | G86: =G80+G84 -> 186.17166 | H86: =H80+H84 -> 165.13946 | I86: =I80+I84 -> 145.13543 | J86: =J80+J84 -> 126.06658
B88: Common Shares | C88: 120 | D88: 120 | E88: 120 | F88: =E88+F50 -> 120 | G88: =F88+G50 -> 120 | H88: =G88+H50 -> 120 | I88: =H88+I50 -> 120 | J88: =I88+J50 -> 120
B89: Retained Earnings | C89: 119.7 | D89: 138.7 | E89: 138.5 | F89: =E89+F29+F51 -> 146.35392 | G89: =F89+G29+G51 -> 159.58221 | H89: =G89+H29+H51 -> 178.20655 | I89: =H89+I29+I51 -> 201.48138 | J89: =I89+J29+J51 -> 229.30096
B90: Shareholder's Equity | C90: =C88+C89 -> 239.7 | D90: =D88+D89 -> 258.7 | E90: =E88+E89 -> 258.5 | F90: =F88+F89 -> 266.35392 | G90: =G88+G89 -> 279.58221 | H90: =H88+H89 -> 298.20655 | I90: =I88+I89 -> 321.48138 | J90: =J88+J89 -> 349.30096
B92: Total Liabilities and Equity | C92: =C86+C90 -> 513.4 | D92: =D86+D90 -> 514.2 | E92: =E86+E90 -> 489.5 | F92: =F86+F90 -> 474.61636 | G92: =G86+G90 -> 465.75388 | H92: =H86+H90 -> 463.34601 | I92: =I86+I90 -> 466.61682 | J92: =J86+J90 -> 475.36754

Sheet Assumptions
B2: Henderson Manufacturing
B3: Forecast Assumptions
B5: ($ Millions unless noted)
B7: Income Statement Drivers | D7: F2022A | E7: F2023A | F7: F2024A | H7: F2025E | I7: F2026E | J7: F2027E | K7: F2028E | L7: F2029E
B8: Revenue Growth % | D8: =(Financials!C8-244.8)/244.8 -> 0 | E8: =(Financials!D8-Financials!C8)/Financials!C8 -> 0.1000817 | F8: =(Financials!E8-Financials!D8)/Financials!D8 -> -0.11177126 | H8: 0.03 | I8: 0.035 | J8: 0.04 | K8: 0.045 | L8: 0.05
B9: Freight % of Gross Revenue | D9: =Financials!C9/Financials!C8 -> 0.12785948 | E9: =Financials!D9/Financials!D8 -> 0.12142592 | F9: =Financials!E9/Financials!E8 -> 0.14381271 | H9: 0.135 | I9: 0.133 | J9: 0.13 | K9: 0.13 | L9: 0.13
B10: Cost of Sales % of Net Revenue | D10: =Financials!C12/Financials!C10 -> 0.74894614 | E10: =Financials!D12/Financials!D10 -> 0.69568893 | F10: =Financials!E12/Financials!E10 -> 0.81982422 | H10: 0.78 | I10: 0.76 | J10: 0.74 | K10: 0.73 | L10: 0.72
B11: SG&A % of Net Revenue | D11: =Financials!C13/Financials!C10 -> 0.015925059 | E11: =Financials!D13/Financials!D10 -> 0.015215554 | F11: =Financials!E13/Financials!E10 -> 0.018554688 | H11: 0.017 | I11: 0.017 | J11: 0.017 | K11: 0.017 | L11: 0.017
B12: Cost Adjustments | D12: =Financials!C16 -> 0 | E12: =Financials!D16 -> 0 | F12: =Financials!E16 -> 0 | H12: 0 | I12: 0 | J12: 0 | K12: 0 | L12: 0
B14: Tax & Depreciation
B15: Depreciation ($M) | D15: =Financials!C19 -> 15.4 | E15: =Financials!D19 -> 15.5 | F15: =Financials!E19 -> 15.8 | H15: 16 | I15: 16.2 | J15: 16.4 | K15: 16.5 | L15: 16.7
B16: Effective Tax Rate | D16: =IF(Financials!C23>0,Financials!C27/Financials!C23,0) -> 0.28787879 | E16: =IF(Financials!D23>0,Financials!D27/Financials!D23,0) -> 0.37467018 | F16: =IF(Financials!E23>0,Financials!E27/Financials!E23,0) -> 0.33333333 | H16: 0.28 | I16: 0.28 | J16: 0.28 | K16: 0.28 | L16: 0.28
B17: Current Tax % of Total Tax | D17: =IF(Financials!C27>0,Financials!C25/Financials!C27,0) -> 0.52631579 | E17: =IF(Financials!D27>0,Financials!D25/Financials!D27,0) -> 0.56338028 | F17: =IF(Financials!E27>0,Financials!E25/Financials!E27,0) -> 0 | H17: 0.6 | I17: 0.6 | J17: 0.6 | K17: 0.6 | L17: 0.6
B19: Working Capital Drivers
B20: AR Days | D20: =Financials!C64/Financials!C10*365 -> 46.159251 | E20: =Financials!D64/Financials!D10*365 -> 42.886729 | F20: =Financials!E64/Financials!E10*365 -> 50.437012 | H20: 46 | I20: 46 | J20: 45 | K20: 45 | L20: 45
B21: Inventory Days (on CoS) | D21: =Financials!C65/Financials!C12*365 -> 83.317699 | E21: =Financials!D65/Financials!D12*365 -> 80.05164 | F21: =Financials!E65/Financials!E12*365 -> 76.304348 | H21: 78 | I21: 78 | J21: 76 | K21: 76 | L21: 76
B22: Prepaid % of Net Revenue | D22: =Financials!C66/Financials!C10 -> 0.068384075 | E22: =Financials!D66/Financials!D10 -> 0.060862215 | F22: =Financials!E66/Financials!E10 -> 0.072753906 | H22: 0.07 | I22: 0.07 | J22: 0.07 | K22: 0.07 | L22: 0.07
B23: Other CA % of Net Revenue | D23: =Financials!C67/Financials!C10 -> 0.006557377 | E23: =Financials!D67/Financials!D10 -> 0.0076077768 | F23: =Financials!E67/Financials!E10 -> 0.005859375 | H23: 0.007 | I23: 0.007 | J23: 0.007 | K23: 0.007 | L23: 0.007
B24: AP Days (on CoS) | D24: =Financials!C78/Financials!C12*365 -> 41.772983 | E24: =Financials!D78/Financials!D12*365 -> 41.467193 | F24: =Financials!E78/Financials!E12*365 -> 39.565217 | H24: 41 | I24: 41 | J24: 41 | K24: 41 | L24: 41
B25: Other CL % of Net Revenue | D25: =Financials!C79/Financials!C10 -> 0.022014052 | E25: =Financials!D79/Financials!D10 -> 0.020710059 | F25: =Financials!E79/Financials!E10 -> 0.0234375 | H25: 0.023 | I25: 0.023 | J25: 0.023 | K25: 0.023 | L25: 0.023
B27: Investing & Financing Drivers
B28: CAPEX ($M) | D28: =-Financials!C43 -> 14.1 | E28: =-Financials!D43 -> 15 | F28: =-Financials!E43 -> 15.5 | H28: 16 | I28: 16.2 | J28: 16.5 | K28: 16.5 | L28: 17
B29: Other Investing CF ($M) | D29: =Financials!C44 -> -5 | E29: =Financials!D44 -> 4 | F29: =Financials!E44 -> 3 | H29: 3 | I29: 3 | J29: 0 | K29: 0 | L29: 0
B30: Interest Rate on Avg Term Debt | E30: =Financials!D22/((Financials!C83+Financials!D83)/2) -> 0.063157895 | F30: =Financials!E22/((Financials!D83+Financials!E83)/2) -> 0.065882353 | H30: 0.065 | I30: 0.065 | J30: 0.065 | K30: 0.065 | L30: 0.065
B31: Term Debt Repayment ($M) | D31: =-Financials!C49 -> 25 | E31: =-Financials!D49 -> 25 | F31: =-Financials!E49 -> 25 | H31: 25 | I31: 25 | J31: 25 | K31: 25 | L31: 25
B32: Revolver Draws / (Repayment) | D32: =Financials!C48 -> 0 | E32: =Financials!D48 -> 0 | F32: =Financials!E48 -> 0 | H32: 0 | I32: 0 | J32: 0 | K32: 0 | L32: 0
B33: Share Issuance / (Buy-Back) | D33: =Financials!C50 -> 0 | E33: =Financials!D50 -> 0 | F33: =Financials!E50 -> 0 | H33: 0 | I33: 0 | J33: 0 | K33: 0 | L33: 0
B34: Common Dividends ($M) | D34: =-Financials!C51 -> 2.8 | E34: =-Financials!D51 -> 4.7 | F34: =-Financials!E51 -> 2.4 | H34: 3 | I34: 3 | J34: 3.5 | K34: 3.5 | L34: 4
B35: Other LTA ($M) | D35: =Financials!C71 -> 19 | E35: =Financials!D71 -> 15 | F35: =Financials!E71 -> 12 | H35: 9 | I35: 6 | J35: 6 | K35: 6 | L35: 6

Sheet Claude Log
A1: Turn # | B1: Date | C1: User Request | D1: Action Taken | E1: Details | F1: Outcome
A2: 1 | B2: 46062 | C2: Build a 5-year forecast from historic actuals in Henderson Manufacturing three-statement model. | D2: Created Assumptions sheet with all drivers; built IS/CFS/BS forecast formulas for F2025E-F2029E on Financials sheet. | E2: Assumptions: Rev growth 3%→5%, CoS margin recovery 78%→72%, SG&A 1.7%, Dep ~$16M, Tax 28%, Interest 6.5% on avg debt, $25M/yr debt paydown, Divs $3-4M. WC driven by days ratios (AR 45-46, Inv 76-78, AP 41). All forecast cells use formulas linked to Assumptions sheet. BS balances all 5 years. | F2: Complete 3-statement model F2025E-F2029E. All BS years balance. Cash goes negative due to aggressive debt repayment from low starting cash ($0.3M). NI recovers from $10.9M to $31.8M. EBITDA recovers from $43.3M to $66.6M. Model is fully dynamic - change any blue assumption to reforecast.
